empack/__init__.py
empack/file_patterns.py
empack/filter_env.py
empack/micromamba_wrapper.py
empack/pack.py
empack/repodata.py
empack/tar_utils.py
empack/version.py
empack/cli/__init__.py
empack/cli/app.py
empack/cli/err.py
empack/cli/main.py
empack/cli/pack.py
empack/cli/repodata.py
empack/cli/version.py
empack-6.0.0.data/data/share/empack/empack_config.yaml
empack-6.0.0.dist-info/METADATA
empack-6.0.0.dist-info/WHEEL
empack-6.0.0.dist-info/entry_points.txt
empack-6.0.0.dist-info/licenses/LICENSE
empack-6.0.0.dist-info/RECORD
