Metadata-Version: 2.4
Name: empack
Version: 6.0.0
Summary: empack emscripten+boa
Project-URL: Homepage, https://github.com/emscripten-forge/empack
Author-email: Thorsten Beier <derthorstenbeier@gmail.com>
License: 
License-File: LICENSE
Keywords: empack
Classifier: Intended Audience :: Developers
Classifier: Natural Language :: English
Classifier: Programming Language :: Python :: 3.8
Classifier: Programming Language :: Python :: 3.9
Classifier: Programming Language :: Python :: 3.10
Classifier: Programming Language :: Python :: 3.11
Requires-Dist: click<8.2
Requires-Dist: networkx
Requires-Dist: platformdirs
Requires-Dist: pyyaml
Requires-Dist: requests
Requires-Dist: typer
Provides-Extra: dev
Requires-Dist: black; extra == 'dev'
Requires-Dist: pre-commit; extra == 'dev'
Requires-Dist: ruff==0.0.262; extra == 'dev'
